niceboard/__init__.py
niceboard/client.py
niceboard/exceptions.py
niceboard/resource.py
niceboard/resources/__init__.py
niceboard/resources/categories.py
niceboard/resources/companies.py
niceboard/resources/geocoding.py
niceboard/resources/job_types.py
niceboard/resources/jobs.py
niceboard/resources/locations.py
niceboard/resources/logo.py
niceboard/services/__init__.py
niceboard/services/search.py
niceboard/services/upload.py
niceboard-0.3.3.dist-info/LICENSE
niceboard-0.3.3.dist-info/METADATA
niceboard-0.3.3.dist-info/WHEEL
niceboard-0.3.3.dist-info/top_level.txt
niceboard-0.3.3.dist-info/RECORD
