Metadata-Version: 2.2
Name: niceboard
Version: 0.3.3
Summary: A Python client for the Niceboard API
Author-email: Dean Singh <dean.singh@gmail.com>
Project-URL: Homepage, https://github.com/workflowing/niceboard
License-File: LICENSE
Requires-Dist: requests>=2.25.0
Requires-Dist: geopy>=2.2.0
Requires-Dist: tenacity>=8.0.0
Provides-Extra: dev
Requires-Dist: pytest>=6.0; extra == "dev"
Requires-Dist: pytest-cov>=2.0; extra == "dev"
Requires-Dist: pytest-mock>=3.10.0; extra == "dev"
Requires-Dist: responses>=0.23.0; extra == "dev"
Requires-Dist: python-dotenv>=1.0.0; extra == "dev"
Requires-Dist: black>=21.0; extra == "dev"
Requires-Dist: isort>=5.0; extra == "dev"
Requires-Dist: mypy>=0.900; extra == "dev"
Requires-Dist: flake8>=3.9; extra == "dev"
Requires-Dist: types-requests>=2.25.0; extra == "dev"
Requires-Dist: twine>=4.0.0; extra == "dev"
